AUTHORS
CHANGELOG
LICENSE
MANIFEST.in
README.rst
setup.py
pyallocine/__init__.py
pyallocine/allocine.py
pyallocine.egg-info/PKG-INFO
pyallocine.egg-info/SOURCES.txt
pyallocine.egg-info/dependency_links.txt
pyallocine.egg-info/not-zip-safe
pyallocine.egg-info/top_level.txt