Metadata-Version: 1.0
Name: pyallocine
Version: 1.0.0
Summary: Parser for allocine.fr
Home-page: http://github.com/gboue/pyallocine
Author: Guillaume Boue
Author-email: guillaumeboue@gmail.com
License: BSD
Keywords: parser allocine
Platform: UNKNOWN
Classifier: Development Status :: 4 - Beta
Classifier: Environment :: Web Environment
Classifier: Intended Audience :: Developers
Classifier: License :: OSI Approved :: BSD License
Classifier: Operating System :: OS Independent
Classifier: Programming Language :: Python
